miding/__init__.py
miding/distribution.py
miding/example_seed.mid
miding/model_1751770203_best.keras
miding/model_1751770954_best.keras
miding/prediction.py
miding/preparation1.py
miding/resources.py
miding-3.2.1.dist-info/licenses/LICENSE.txt
miding-3.2.1.dist-info/METADATA
miding-3.2.1.dist-info/WHEEL
miding-3.2.1.dist-info/entry_points.txt
miding-3.2.1.dist-info/top_level.txt
miding-3.2.1.dist-info/RECORD
