Metadata-Version: 2.4
Name: miding
Version: 3.2.1
Summary: A generator of midi score based on GRU.
Author-email: Jerry_Skywolf <jerryskywolf@outlook.com>
License-Expression: GPL-3.0
Project-URL: Homepage, https://github.com/JerrySkywolf/miding
Project-URL: Issues, https://github.com/JerrySkywolf/miding/issues
Project-URL: DOWNLOAD, https://github.com/JerrySkywolf/miding/releases
Keywords: midi,miding,neuronal,generate,music,Jerry Skywolf
Classifier: Programming Language :: Python :: 3.11
Classifier: Operating System :: OS Independent
Classifier: Development Status :: 5 - Production/Stable
Requires-Python: >=3.9
License-File: LICENSE.txt
Requires-Dist: keras
Requires-Dist: mido
Requires-Dist: numpy
Requires-Dist: tensorflow
Dynamic: license-file
